flask_bigapp/__init__.py
flask_bigapp/auth.py
flask_bigapp/bigapp.py
flask_bigapp/blueprint.py
flask_bigapp/helpers.py
flask_bigapp/orm.py
flask_bigapp/registeries.py
flask_bigapp/resources.py
flask_bigapp/security.py
flask_bigapp/utilities.py
flask_bigapp_cli/__init__.py
flask_bigapp_cli/cli.py
flask_bigapp_cli/resources.py
flask_bigapp_cli/__temp_theme_dir__/builtins/context_processors.py
flask_bigapp_cli/__temp_theme_dir__/builtins/filters.py
flask_bigapp_cli/__temp_theme_dir__/static/css/example__css.css
flask_bigapp_cli/__temp_theme_dir__/static/img/Flask-BigApp-Logo.png
flask_bigapp_cli/__temp_theme_dir__/static/js/example__js.js
flask_bigapp_cli/__temp_theme_dir__/templates/__temp_theme_dir__/errors/400.html
flask_bigapp_cli/__temp_theme_dir__/templates/__temp_theme_dir__/errors/401.html
flask_bigapp_cli/__temp_theme_dir__/templates/__temp_theme_dir__/errors/403.html
flask_bigapp_cli/__temp_theme_dir__/templates/__temp_theme_dir__/errors/404.html
flask_bigapp_cli/__temp_theme_dir__/templates/__temp_theme_dir__/errors/405.html
flask_bigapp_cli/__temp_theme_dir__/templates/__temp_theme_dir__/errors/500.html
flask_bigapp_cli/__temp_theme_dir__/templates/__temp_theme_dir__/extends/main.html
flask_bigapp_cli/__temp_theme_dir__/templates/__temp_theme_dir__/includes/footer.html
flask_bigapp_cli/__temp_theme_dir__/templates/__temp_theme_dir__/includes/menu.html
Flask_BigApp-2023.1.9.7.dist-info/LICENSE
Flask_BigApp-2023.1.9.7.dist-info/METADATA
Flask_BigApp-2023.1.9.7.dist-info/WHEEL
Flask_BigApp-2023.1.9.7.dist-info/entry_points.txt
Flask_BigApp-2023.1.9.7.dist-info/top_level.txt
Flask_BigApp-2023.1.9.7.dist-info/RECORD
